claude_api.py
claude_api-1.0.16.dist-info/LICENSE
claude_api-1.0.16.dist-info/METADATA
claude_api-1.0.16.dist-info/WHEEL
claude_api-1.0.16.dist-info/top_level.txt
claude_api-1.0.16.dist-info/RECORD
